currint/__init__.py
currint/amount.py
currint/currency.py
currint/tests/__init__.py
currint/tests/test_amount.py
currint/tests/test_currency.py
currint-2.0.0.dist-info/DESCRIPTION.rst
currint-2.0.0.dist-info/METADATA
currint-2.0.0.dist-info/RECORD
currint-2.0.0.dist-info/WHEEL
currint-2.0.0.dist-info/metadata.json
currint-2.0.0.dist-info/top_level.txt
